bayesian_hmm/__init__.py
bayesian_hmm/chain.py
bayesian_hmm/hdphmm.py
bayesian_hmm/utils.py
bayesian_hmm-0.0.4.dist-info/LICENSE
bayesian_hmm-0.0.4.dist-info/METADATA
bayesian_hmm-0.0.4.dist-info/WHEEL
bayesian_hmm-0.0.4.dist-info/top_level.txt
bayesian_hmm-0.0.4.dist-info/RECORD
