Metadata-Version: 2.1
Name: bayesian-hmm
Version: 0.0.4
Summary: A non-parametric Bayesian approach to Hidden Markov Models
Home-page: https://github.com/jamesross2/Bayesian-HMM
Author: James Ross
Author-email: jamespatross@gmail.com
License: MIT
Platform: UNKNOWN
Classifier: Programming Language :: Python :: 3
Classifier: License :: OSI Approved :: MIT License
Classifier: Operating System :: OS Independent
Requires-Dist: numpy
Requires-Dist: scipy
Requires-Dist: sympy
Requires-Dist: terminaltables
Requires-Dist: tqdm
